MANIFEST.in
README.md
requirements.txt
setup.cfg
setup.py
cl_gym/__init__.py
cl_gym.egg-info/PKG-INFO
cl_gym.egg-info/SOURCES.txt
cl_gym.egg-info/dependency_links.txt
cl_gym.egg-info/requires.txt
cl_gym.egg-info/top_level.txt
cl_gym/algorithms/__init__.py
cl_gym/algorithms/agem.py
cl_gym/algorithms/base.py
cl_gym/algorithms/er_ring.py
cl_gym/algorithms/ewc.py
cl_gym/algorithms/mcsgd.py
cl_gym/algorithms/mtl.py
cl_gym/algorithms/ogd.py
cl_gym/algorithms/utils.py
cl_gym/backbones/__init__.py
cl_gym/backbones/base.py
cl_gym/backbones/cnn.py
cl_gym/backbones/mlp.py
cl_gym/backbones/resnet.py
cl_gym/benchmarks/__init__.py
cl_gym/benchmarks/base.py
cl_gym/benchmarks/cifar.py
cl_gym/benchmarks/mixed.py
cl_gym/benchmarks/mnist.py
cl_gym/benchmarks/pamap2.py
cl_gym/benchmarks/toy_1D_reg.py
cl_gym/benchmarks/toy_2D_clf.py
cl_gym/benchmarks/transforms.py
cl_gym/benchmarks/utils.py
cl_gym/trainer/__init__.py
cl_gym/trainer/base.py
cl_gym/trainer/callback_hooks.py
cl_gym/trainer/state_manager.py
cl_gym/utils/__init__.py
cl_gym/utils/loggers.py
cl_gym/utils/callbacks/__init__.py
cl_gym/utils/callbacks/base.py
cl_gym/utils/callbacks/experiment_manager.py
cl_gym/utils/callbacks/helpers.py
cl_gym/utils/callbacks/metric_manager.py
cl_gym/utils/callbacks/model.py
cl_gym/utils/metrics/__init__.py
cl_gym/utils/metrics/accuracy.py
cl_gym/utils/metrics/base.py
cl_gym/utils/metrics/forgetting.py